spdx_license_matcher/__init__.py
spdx_license_matcher/base_matcher.py
spdx_license_matcher/find.py
spdx_license_matcher/license_loader.py
spdx_license_matcher/main.py
spdx_license_matcher/matcher_utils.py
spdx_license_matcher/matchers.py
spdx_license_matcher/normalize.py
spdx_license_matcher/py.typed
spdx_license_matcher/regex_matcher.py
spdx_license_matcher/test_all_licenses.py
spdx_license_matcher/test_license_loader.py
spdx_license_matcher/test_normalize_unbox.py
spdx_license_matcher/transformer.py
spdx_license_matcher/word_variants.py
spdx_license_matcher/licenses/0BSD.xml
spdx_license_matcher/licenses/3D-Slicer-1.0.xml
spdx_license_matcher/licenses/AAL.xml
spdx_license_matcher/licenses/ADSL.xml
spdx_license_matcher/licenses/AFL-1.1.xml
spdx_license_matcher/licenses/AFL-1.2.xml
spdx_license_matcher/licenses/AFL-2.0.xml
spdx_license_matcher/licenses/AFL-2.1.xml
spdx_license_matcher/licenses/AFL-3.0.xml
spdx_license_matcher/licenses/AGPL-1.0-only.xml
spdx_license_matcher/licenses/AGPL-1.0-or-later.xml
spdx_license_matcher/licenses/AGPL-1.0.xml
spdx_license_matcher/licenses/AGPL-3.0-only.xml
spdx_license_matcher/licenses/AGPL-3.0-or-later.xml
spdx_license_matcher/licenses/AGPL-3.0.xml
spdx_license_matcher/licenses/AMD-newlib.xml
spdx_license_matcher/licenses/AMDPLPA.xml
spdx_license_matcher/licenses/AML-glslang.xml
spdx_license_matcher/licenses/AML.xml
spdx_license_matcher/licenses/AMPAS.xml
spdx_license_matcher/licenses/ANTLR-PD-fallback.xml
spdx_license_matcher/licenses/ANTLR-PD.xml
spdx_license_matcher/licenses/APAFML.xml
spdx_license_matcher/licenses/APL-1.0.xml
spdx_license_matcher/licenses/APSL-1.0.xml
spdx_license_matcher/licenses/APSL-1.1.xml
spdx_license_matcher/licenses/APSL-1.2.xml
spdx_license_matcher/licenses/APSL-2.0.xml
spdx_license_matcher/licenses/ASWF-Digital-Assets-1.0.xml
spdx_license_matcher/licenses/ASWF-Digital-Assets-1.1.xml
spdx_license_matcher/licenses/Abstyles.xml
spdx_license_matcher/licenses/AdaCore-doc.xml
spdx_license_matcher-1.0.10.dist-info/licenses/LICENSE
spdx_license_matcher-1.0.10.dist-info/METADATA
spdx_license_matcher-1.0.10.dist-info/WHEEL
spdx_license_matcher-1.0.10.dist-info/entry_points.txt
spdx_license_matcher-1.0.10.dist-info/top_level.txt
spdx_license_matcher-1.0.10.dist-info/RECORD
