Metadata-Version: 2.4
Name: spdx-license-matcher
Version: 1.0.10
Summary: Tool for matching and working with SPDX licenses
Author: Sean Ross-Ross
License-Expression: MIT
Project-URL: Source, https://github.com/openteamsinc/spdx_matcher
Classifier: Intended Audience :: Developers
Requires-Python: >=3.8
License-File: LICENSE
Requires-Dist: lxml~=5.4.0
Requires-Dist: click~=8.2.1
Provides-Extra: dev
Requires-Dist: pytest>=7.0.0; extra == "dev"
Requires-Dist: black>=23.0.0; extra == "dev"
Requires-Dist: isort>=5.10.0; extra == "dev"
Requires-Dist: mypy>=1.0.0; extra == "dev"
Requires-Dist: ruff>=0.0.250; extra == "dev"
Dynamic: license-file
